setup.py
imaper/__init__.py
imaper/parser.py
imaper.egg-info/PKG-INFO
imaper.egg-info/SOURCES.txt
imaper.egg-info/dependency_links.txt
imaper.egg-info/requires.txt
imaper.egg-info/top_level.txt