Metadata-Version: 1.0
Name: imaper
Version: 1.0.0
Summary: IMAP made easy.
Home-page: https://bitbucket.org/dhrrgn/imaper
Author: Dan Horrigan
Author-email: dan@dhorrigan.com
License: MIT
Platform: UNKNOWN
Classifier: Topic :: Utilities
